MANIFEST.in
setup.py
docs/HISTORY.txt
docs/TODO.txt
pymassmailer/__init__.py
pymassmailer.egg-info/PKG-INFO
pymassmailer.egg-info/SOURCES.txt
pymassmailer.egg-info/dependency_links.txt
pymassmailer.egg-info/entry_points.txt
pymassmailer.egg-info/not-zip-safe
pymassmailer.egg-info/requires.txt
pymassmailer.egg-info/top_level.txt