Metadata-Version: 1.1
Name: pymassmailer
Version: 1.1
Summary: Mass Mailer using mallow mailer and jinja2 templates
Home-page: https://github.com/hur1can3/pymassmailer
Author: Matthew Levandowski
Author-email: levandowski.matthew@gmail.com
License: Apache
Keywords: EMAIL SMTP JINJA
Platform: UNKNOWN
Classifier: Programming Language :: Python
Classifier: Topic :: Software Development :: Libraries :: Python Modules
Classifier: Development Status :: 4 - Beta
Classifier: License :: OSI Approved :: Apache Software License
